Metadata-Version: 2.1
Name: fast-multi-regex
Version: 0.18
Summary: Fast multi-regex, multi-pattern, boolean expression matching
Home-page: https://github.com/aitsc/fast_multi_regex
Author: tanshicheng
License: GPLv3
Keywords: tools
Classifier: Intended Audience :: Developers
Classifier: License :: OSI Approved :: GNU General Public License v3 (GPLv3)
Classifier: Programming Language :: Python :: 3 :: Only
Classifier: Topic :: Software Development :: Libraries
Requires-Python: >=3.9
License-File: LICENSE
